<?xml version="1.0" encoding="utf-8" ?>
<LanguageData>
  <CBKF.Settings.BarPosition>Colonist Bar Position</CBKF.Settings.BarPosition>
  <CBKF.Settings.BaseSpacingHorizontal>Horizontaler Abstand</CBKF.Settings.BaseSpacingHorizontal>
  <CBKF.Settings.BaseSpacingVertical>Vertikaler Abstand</CBKF.Settings.BaseSpacingVertical>
  <CBKF.Settings.BasicSize>Maximale Icon-Größe</CBKF.Settings.BasicSize>
  <CBKF.Settings.DoubleClickTime>Doppelklick-Intervall</CBKF.Settings.DoubleClickTime>
  <CBKF.Settings.FemaleColor>Farbe für weibliche Kolonisten</CBKF.Settings.FemaleColor>
  <CBKF.Settings.FixedScale>Keine Skalierung</CBKF.Settings.FixedScale>
  <CBKF.Settings.MaleColor>Farbe für männliche Kolonisten</CBKF.Settings.MaleColor>
  <CBKF.Settings.MarginBottom>Unterer Abstand</CBKF.Settings.MarginBottom>
  <CBKF.Settings.MarginEdge>Abstand Rand</CBKF.Settings.MarginEdge>
  <CBKF.Settings.MarginLeft>Linker Abstand</CBKF.Settings.MarginLeft>
  <CBKF.Settings.MarginRight>Rechter Abstand</CBKF.Settings.MarginRight>
  <CBKF.Settings.MarginTop>Oberer Abstand</CBKF.Settings.MarginTop>
  <CBKF.Settings.MaxColonistBarHeight>Maximale Leistenhöhe</CBKF.Settings.MaxColonistBarHeight>
  <CBKF.Settings.PawnTextureCameraHorizontalOffset>Kamera Versatz horizontal</CBKF.Settings.PawnTextureCameraHorizontalOffset>
  <CBKF.Settings.PawnTextureCameraVerticalOffset>Kamera Versatz vertikal</CBKF.Settings.PawnTextureCameraVerticalOffset>
  <CBKF.Settings.PawnTextureCameraZoom>Kamera Zoom</CBKF.Settings.PawnTextureCameraZoom>
  <CBKF.Settings.ResetColors>Farben zurücksetzen</CBKF.Settings.ResetColors>
  <CBKF.Settings.RevertSettings>Einstellungen zurücksetzen</CBKF.Settings.RevertSettings>
  <CBKF.Settings.useBottom>Unten</CBKF.Settings.useBottom>
  <CBKF.Settings.useGender>Hintergrundfarbe nach Geschlecht</CBKF.Settings.useGender>
  <CBKF.Settings.useLeft>Links</CBKF.Settings.useLeft>
  <CBKF.Settings.useRight>Rechts</CBKF.Settings.useRight>
  <CBKF.Settings.useTop>Top</CBKF.Settings.useTop>
  <CBKF.Settings.UseMoodColors>Zeige Stimmung im Hintergrund</CBKF.Settings.UseMoodColors>

  <CBKF.Settings.SortBy>Sortieren nach</CBKF.Settings.SortBy>
  <CBKF.Settings.Vanilla>Vanilla</CBKF.Settings.Vanilla>
  <CBKF.Settings.SexAge>Geschlecht dann Alter</CBKF.Settings.SexAge>
  <CBKF.Settings.Mood>Stimmung</CBKF.Settings.Mood>
  <CBKF.Settings.Health>Gesundheit</CBKF.Settings.Health>
  <CBKF.Settings.Medic>Medizin</CBKF.Settings.Medic>
  <CBKF.Settings.Weapons>Waffen</CBKF.Settings.Weapons>
  <CBKF.Settings.SortingOptions>Sortierungs-Optionen</CBKF.Settings.SortingOptions>
  <CBKF.Settings.UseWeaponIcons>Benutze Icons für Waffen</CBKF.Settings.UseWeaponIcons>
  <CBKF.Settings.ByName>Nach Name</CBKF.Settings.ByName>
  <CBKF.Settings.barSettings>Colonist Bar Einstellungen </CBKF.Settings.barSettings>
  <CBKF.Settings.useZoomToMouse>Benutze ZoomToMouse</CBKF.Settings.useZoomToMouse>
  
  <FollowMe.Cancel> {0} wird nicht mehr Verfolgt.</FollowMe.Cancel>
  <FollowMe.Follow> Verfolge jetzt {0}.</FollowMe.Follow>

  <FollowMe.RejectMultiple>Können nicht verfolgt werden, zu viele Ziele.</FollowMe.RejectMultiple>
  <FollowMe.RejectNoSelection>Kann nicht folgen, kein Ziel.</FollowMe.RejectNoSelection>
  <FollowMe.RejectNotAThing>Kann nicht folgen, Markierung ist kein Individuum.</FollowMe.RejectNotAThing>

  <PSI.Enabled>Pawn State Icons aktiviert</PSI.Enabled>
  <PSI.Disabled>Pawn State Icons deaktiviert. Drücke F11 zum Reaktivieren</PSI.Disabled>
  <PSI.Settings.IconSet>Icon Set: </PSI.Settings.IconSet>
  <PSI.Settings.Advanced>Erweitert</PSI.Settings.Advanced>
  <PSI.Settings.VisibilityButton>Sichtbarkeit</PSI.Settings.VisibilityButton>
  <PSI.Settings.ArrangementButton>Größe &amp; Anordnung</PSI.Settings.ArrangementButton>
  <PSI.Settings.SensitivityButton>Empfindlihckeit</PSI.Settings.SensitivityButton>

  <PSI.Settings.LoadPresetButton>Lade Voreinstellung</PSI.Settings.LoadPresetButton>
  <PSI.Settings.LoadPreset.UnableToLoad>Konnte Voreinstellung nicht laden: </PSI.Settings.LoadPreset.UnableToLoad>
  <PSI.Settings.ReturnButton>Zurück</PSI.Settings.ReturnButton>

  <PSI.Settings.SizeLabel.0>kaum sichtbar</PSI.Settings.SizeLabel.0>
  <PSI.Settings.SizeLabel.1>winzig</PSI.Settings.SizeLabel.1>
  <PSI.Settings.SizeLabel.2>sehr klein</PSI.Settings.SizeLabel.2>
  <PSI.Settings.SizeLabel.3>klein</PSI.Settings.SizeLabel.3>
  <PSI.Settings.SizeLabel.4>moderat</PSI.Settings.SizeLabel.4>
  <PSI.Settings.SizeLabel.5>moderat</PSI.Settings.SizeLabel.5>
  <PSI.Settings.SizeLabel.6>groß</PSI.Settings.SizeLabel.6>
  <PSI.Settings.SizeLabel.7>sehr groß</PSI.Settings.SizeLabel.7>
  <PSI.Settings.SizeLabel.8>enormous</PSI.Settings.SizeLabel.8>

  <PSI.Settings.Visibility.Header>Sichbarkeit</PSI.Settings.Visibility.Header>
  <PSI.Settings.Visibility.TargetPoint>Wegpunkt</PSI.Settings.Visibility.TargetPoint>
  <PSI.Settings.Visibility.Aggressive>Aggressiv</PSI.Settings.Visibility.Aggressive>
  <PSI.Settings.Visibility.Dazed>Verwirrt</PSI.Settings.Visibility.Dazed>
  <PSI.Settings.Visibility.Leave>Geht</PSI.Settings.Visibility.Leave>
  <PSI.Settings.Visibility.Draft>Im Anschlag</PSI.Settings.Visibility.Draft>
  <PSI.Settings.Visibility.Idle>Untätig</PSI.Settings.Visibility.Idle>
  <PSI.Settings.Visibility.Unarmed>Unbewaffnet</PSI.Settings.Visibility.Unarmed>
  <PSI.Settings.Visibility.Hungry>Hungrig</PSI.Settings.Visibility.Hungry>
  <PSI.Settings.Visibility.Sad>Traurig</PSI.Settings.Visibility.Sad>
  <PSI.Settings.Visibility.Tired>Müde</PSI.Settings.Visibility.Tired>
  <PSI.Settings.Visibility.Disease>Krankheit</PSI.Settings.Visibility.Disease>
  <PSI.Settings.Visibility.Injury>Verletzung</PSI.Settings.Visibility.Injury>
  <PSI.Settings.Visibility.Bloodloss>Blutverlust</PSI.Settings.Visibility.Bloodloss>
  <PSI.Settings.Visibility.Hot>Heiß</PSI.Settings.Visibility.Hot>
  <PSI.Settings.Visibility.Cold>Kalt</PSI.Settings.Visibility.Cold>
  <PSI.Settings.Visibility.Naked>Nackt</PSI.Settings.Visibility.Naked>
  <PSI.Settings.Visibility.Drunk>Betrunken</PSI.Settings.Visibility.Drunk>
  <PSI.Settings.Visibility.Pacific>Pacifist</PSI.Settings.Visibility.Pacific>
  <PSI.Settings.Visibility.ApparelHealth>Ausgefranste Kleidung</PSI.Settings.Visibility.ApparelHealth>

  <PSI.Settings.Sensitivity.Header>Empfindlichkeit</PSI.Settings.Sensitivity.Header>
  <PSI.Settings.Sensitivity.Bleeding>Blutung: </PSI.Settings.Sensitivity.Bleeding>
  <PSI.Settings.Sensitivity.Injured>Verletzt wenn Efiizienz &lt; </PSI.Settings.Sensitivity.Injured>
  <PSI.Settings.Sensitivity.Food>Hungrig wenn Nahrung &lt; </PSI.Settings.Sensitivity.Food>
  <PSI.Settings.Sensitivity.Mood>Traurig wenn Stimmung &lt; </PSI.Settings.Sensitivity.Mood>
  <PSI.Settings.Sensitivity.Rest>Müde wenn Ruhe &lt; </PSI.Settings.Sensitivity.Rest>
  <PSI.Settings.Sensitivity.ApparelHealth>Ausgefranst wenn Zustand &lt; </PSI.Settings.Sensitivity.ApparelHealth>
  <PSI.Settings.Sensitivity.Temperature>Erhöhe die Temperaturweite: </PSI.Settings.Sensitivity.Temperature>

  <PSI.Settings.Sensitivity.Bleeding.0>sehr niedrig</PSI.Settings.Sensitivity.Bleeding.0>
  <PSI.Settings.Sensitivity.Bleeding.1>niedrig</PSI.Settings.Sensitivity.Bleeding.1>
  <PSI.Settings.Sensitivity.Bleeding.2>mittel</PSI.Settings.Sensitivity.Bleeding.2>
  <PSI.Settings.Sensitivity.Bleeding.3>mittel</PSI.Settings.Sensitivity.Bleeding.3>
  <PSI.Settings.Sensitivity.Bleeding.4>hoch</PSI.Settings.Sensitivity.Bleeding.4>
  <PSI.Settings.Sensitivity.Bleeding.5>sehr hoch</PSI.Settings.Sensitivity.Bleeding.5>
  <PSI.Settings.Sensitivity.Bleeding.6>sehr hoch</PSI.Settings.Sensitivity.Bleeding.6>

  <PSI.Settings.Arrangement.Header>Größe &amp; Anordnung</PSI.Settings.Arrangement.Header>
  <PSI.Settings.Arrangement.IconSize>Icon Größe: </PSI.Settings.Arrangement.IconSize>
  <PSI.Settings.Arrangement.IconPosition>Position: </PSI.Settings.Arrangement.IconPosition>
  <PSI.Settings.Arrangement.IconOffset>Abstand dazwischen: </PSI.Settings.Arrangement.IconOffset>
  <PSI.Settings.Arrangement.Horizontal>Horizontale Anordnung</PSI.Settings.Arrangement.Horizontal>
  <PSI.Settings.Arrangement.ScreenScale>Bildschirm-skalierte Icons</PSI.Settings.Arrangement.ScreenScale>
  <PSI.Settings.Arrangement.IconsPerColumn>Icons pro Reihe: </PSI.Settings.Arrangement.IconsPerColumn>

</LanguageData>